skulk/VERSION
skulk/__init__.py
skulk/bumper.py
skulk/questions.py
skulk/questions_fallback.py
skulk/skulk.py
skulk/skulk_parse.py
skulk/util.py
skulk-3.1.3.dist-info/METADATA
skulk-3.1.3.dist-info/WHEEL
skulk-3.1.3.dist-info/entry_points.txt
skulk-3.1.3.dist-info/top_level.txt
skulk-3.1.3.dist-info/RECORD
