Metadata-Version: 2.1
Name: skulk
Version: 3.1.3
Summary: Streamline release for Conductor client tools and others
Home-page: https://github.com/ConductorTechnologies/skulk
Author: Julian Mann
Author-email: julian@conductortech.com
Classifier: Operating System :: OS Independent
Classifier: Programming Language :: Python
Classifier: Programming Language :: Python
Requires-Dist: GitPython<4.0.0,>=3.1.31
Requires-Dist: semver<4.0.0,>=3.0.0
Requires-Dist: twine>=4.0.2
Requires-Dist: future>=0.18.3
Requires-Dist: bullet>=2.2.0
Requires-Dist: tabulate>=0.9.0
Requires-Dist: Click
